gpustatapi/__init__.py
gpustatapi/app.py
gpustatapi-0.1.dist-info/METADATA
gpustatapi-0.1.dist-info/WHEEL
gpustatapi-0.1.dist-info/entry_points.txt
gpustatapi-0.1.dist-info/top_level.txt
gpustatapi-0.1.dist-info/RECORD
