Metadata-Version: 2.1
Name: gpustatapi
Version: 0.1
Summary: Simple API Wrapper for gpustat
Home-page: https://github.com/yueyericardo/gpustatapi
Author: Richard Xue
Author-email: yueyericardo@gmail.com
License: Apache License 2.0
Platform: UNKNOWN
Requires-Dist: gpustat
